.gitignore
MANIFEST.in
README.rst
setup.cfg
setup.py
docs/HISTORY.txt
docs/INSTALL.txt
docs/LICENSE.GPL
docs/LICENSE.txt
slc/__init__.py
slc.facetedcalendar.egg-info/PKG-INFO
slc.facetedcalendar.egg-info/SOURCES.txt
slc.facetedcalendar.egg-info/dependency_links.txt
slc.facetedcalendar.egg-info/entry_points.txt
slc.facetedcalendar.egg-info/namespace_packages.txt
slc.facetedcalendar.egg-info/not-zip-safe
slc.facetedcalendar.egg-info/paster_plugins.txt
slc.facetedcalendar.egg-info/requires.txt
slc.facetedcalendar.egg-info/top_level.txt
slc/facetedcalendar/__init__.py
slc/facetedcalendar/adapter.py
slc/facetedcalendar/configure.zcml
slc/facetedcalendar/interfaces.py
slc/facetedcalendar/tests.py
slc/facetedcalendar/utils.py
slc/facetedcalendar/vocabulary.py
slc/facetedcalendar/browser/__init__.py
slc/facetedcalendar/browser/ajax.py
slc/facetedcalendar/browser/configure.zcml
slc/facetedcalendar/browser/facets.py
slc/facetedcalendar/browser/form.py
slc/facetedcalendar/browser/interfaces.py
slc/facetedcalendar/browser/view.py
slc/facetedcalendar/browser/javascripts/fullcalendar.js
slc/facetedcalendar/browser/javascripts/main.js
slc/facetedcalendar/browser/stylesheets/main.css
slc/facetedcalendar/browser/templates/faceted_parameters_box.pt
slc/facetedcalendar/browser/templates/facets.pt
slc/facetedcalendar/browser/templates/facets_config.pt
slc/facetedcalendar/browser/templates/view.pt
slc/facetedcalendar/profiles/default/browserlayer.xml
slc/facetedcalendar/profiles/default/cssregistry.xml
slc/facetedcalendar/profiles/default/jsregistry.xml
slc/facetedcalendar/profiles/default/metadata.xml
slc/facetedcalendar/profiles/default/types/Topic.xml