Metadata-Version: 1.0
Name: slc.facetedcalendar
Version: 0.3
Summary: UNKNOWN
Home-page: http://svn.plone.org/svn/collective/
Author: UNKNOWN
Author-email: UNKNOWN
License: GPL
Platform: UNKNOWN
Classifier: Framework :: Plone :: 4.1
Classifier: Programming Language :: Python
